[
  {
    "id_str": "1800000000000199905",
    "created_at": "2025-01-24T08:10:15Z",
    "text": "Udah sebulan pakai Touring-3000 Blue, oke terus — sampai lebih cepat, aman Bakal beli lagi. 👍",
    "lang": "in",
    "user": {
      "id_str": "5861325877",
      "name": "Rizky Lopez",
      "screen_name": "rizklope7493",
      "followers_count": 1948,
      "verified": false
    },
    "retweet_count": 17,
    "favorite_count": 39,
    "source": "Twitter Web App",
    "_meta": {
      "sentiment": "positive",
      "aspect": "pengiriman",
      "product": "Touring-3000 Blue, 50",
      "category": "Unknown",
      "subcategory": "Unknown",
      "product_bias": "mixed",
      "spike": false
    }
  },
  {
    "id_str": "1800000000000199960",
    "created_at": "2025-01-24T08:17:24Z",
    "text": "Naik level gowes ku gara-gara Women's Mountain Shorts — sampai lebih cepat, aman ✨ #AWcycles",
    "lang": "in",
    "user": {
      "id_str": "2632837049",
      "name": "Hannah Clark",
      "screen_name": "hannclar8504",
      "followers_count": 1538,
      "verified": false
    },
    "retweet_count": 9,
    "favorite_count": 8,
    "source": "Twitter for iPhone",
    "_meta": {
      "sentiment": "positive",
      "aspect": "pengiriman",
      "product": "Women's Mountain Shorts, L",
      "category": "Unknown",
      "subcategory": "Unknown",
      "product_bias": "mixed",
      "spike": false
    }
  },
  {
    "id_str": "1800000000000199855",
    "created_at": "2025-01-24T10:19:52Z",
    "text": "Regret buying the Lock Nut 22 — way too expensive Do better AWC. #AWcycles #AdventureWorks #cycling #Unknown",
    "lang": "en",
    "user": {
      "id_str": "4460314218",
      "name": "Sam Santoso",
      "screen_name": "samsant691",
      "followers_count": 4418,
      "verified": false
    },
    "retweet_count": 1,
    "favorite_count": 37,
    "source": "Twitter for Android",
    "_meta": {
      "sentiment": "negative",
      "aspect": "harga",
      "product": "Lock Nut 22",
      "category": "Unknown",
      "subcategory": "Unknown",
      "product_bias": "mixed",
      "spike": false
    }
  },
  {
    "id_str": "1800000000000199988",
    "created_at": "2025-01-24T15:57:42Z",
    "text": "So glad I picked up the Seat Tube — still rock solid after months Five stars.",
    "lang": "en",
    "user": {
      "id_str": "5334337522",
      "name": "Dimas Lee",
      "screen_name": "dimalee5555",
      "followers_count": 246,
      "verified": false
    },
    "retweet_count": 14,
    "favorite_count": 42,
    "source": "Twitter Web App",
    "_meta": {
      "sentiment": "positive",
      "aspect": "durabilitas",
      "product": "Seat Tube",
      "category": "Unknown",
      "subcategory": "Unknown",
      "product_bias": "loved",
      "spike": false
    }
  },
  {
    "id_str": "1800000000000199926",
    "created_at": "2025-01-24T16:44:49Z",
    "text": "Udah sebulan pakai Mountain-300 Black, oke terus — admin responsif banget Recommended. 🚴",
    "lang": "in",
    "user": {
      "id_str": "3146784882",
      "name": "Eko Nguyen",
      "screen_name": "ekonguy3506",
      "followers_count": 16,
      "verified": false
    },
    "retweet_count": 21,
    "favorite_count": 30,
    "source": "Twitter for iPhone",
    "_meta": {
      "sentiment": "positive",
      "aspect": "layanan",
      "product": "Mountain-300 Black, 40",
      "category": "Unknown",
      "subcategory": "Unknown",
      "product_bias": "loved",
      "spike": false
    }
  },
  {
    "id_str": "1800000000000199793",
    "created_at": "2025-01-24T16:56:35Z",
    "text": "So glad I picked up the Flat Washer 2 — the team was super helpful Highly recommend. 🚴 #rideon #cycling #Unknown",
    "lang": "en",
    "user": {
      "id_str": "7215523861",
      "name": "Kevin Halim",
      "screen_name": "kevihali642",
      "followers_count": 0,
      "verified": false
    },
    "retweet_count": 9,
    "favorite_count": 12,
    "source": "Twitter for Android",
    "_meta": {
      "sentiment": "positive",
      "aspect": "layanan",
      "product": "Flat Washer 2",
      "category": "Unknown",
      "subcategory": "Unknown",
      "product_bias": "loved",
      "spike": false
    }
  },
  {
    "id_str": "1800000000000199747",
    "created_at": "2025-01-24T20:34:30Z",
    "text": "Suka banget sama Touring-1000 Blue dari AWC — sampai lebih cepat, aman 🚴",
    "lang": "in",
    "user": {
      "id_str": "3938145703",
      "name": "Sofia Garcia",
      "screen_name": "sofigarc152",
      "followers_count": 3184,
      "verified": false
    },
    "retweet_count": 15,
    "favorite_count": 14,
    "source": "Twitter for Android",
    "_meta": {
      "sentiment": "positive",
      "aspect": "pengiriman",
      "product": "Touring-1000 Blue, 46",
      "category": "Unknown",
      "subcategory": "Unknown",
      "product_bias": "mixed",
      "spike": false
    }
  },
  {
    "id_str": "1800000000000199836",
    "created_at": "2025-01-24T20:51:16Z",
    "text": "Really impressed with the HL Crankarm — worth every penny 👍 #AdventureWorks #bikelife",
    "lang": "en",
    "user": {
      "id_str": "8442334556",
      "name": "Alex Nguyen",
      "screen_name": "alexnguy9492",
      "followers_count": 36,
      "verified": false
    },
    "retweet_count": 7,
    "favorite_count": 23,
    "source": "Twitter for iPhone",
    "_meta": {
      "sentiment": "positive",
      "aspect": "harga",
      "product": "HL Crankarm",
      "category": "Unknown",
      "subcategory": "Unknown",
      "product_bias": "loved",
      "spike": false
    }
  }
]