[
  {
    "id_str": "1800000000000224139",
    "created_at": "2025-05-23T09:58:52Z",
    "text": "So glad I picked up the Touring Front Wheel — performs flawlessly Highly recommend. 🚴 #cycling #Unknown",
    "lang": "en",
    "user": {
      "id_str": "368919990",
      "name": "Nadia Lee",
      "screen_name": "nadilee4868",
      "followers_count": 821,
      "verified": false
    },
    "retweet_count": 7,
    "favorite_count": 16,
    "source": "Twitter for Android",
    "_meta": {
      "sentiment": "positive",
      "aspect": "kualitas",
      "product": "Touring Front Wheel",
      "category": "Unknown",
      "subcategory": "Unknown",
      "product_bias": "mixed",
      "spike": false
    }
  },
  {
    "id_str": "1800000000000224174",
    "created_at": "2025-05-23T11:27:43Z",
    "text": "Salut buat AdventureWorks Cycles soal ML Road Pedal — tahan banting dipakai berat Nggak nyesel. 😍",
    "lang": "in",
    "user": {
      "id_str": "6829956619",
      "name": "Maya Putra",
      "screen_name": "mayaputr9946",
      "followers_count": 620,
      "verified": false
    },
    "retweet_count": 0,
    "favorite_count": 42,
    "source": "Twitter for Android",
    "_meta": {
      "sentiment": "positive",
      "aspect": "durabilitas",
      "product": "ML Road Pedal",
      "category": "Unknown",
      "subcategory": "Unknown",
      "product_bias": "problem",
      "spike": false
    }
  },
  {
    "id_str": "1800000000000224178",
    "created_at": "2025-05-23T15:18:59Z",
    "text": "Ada yang pakai ML Road Seat/Saddle dari AdventureWorks? Worth it nggak? 🤷 #MTB",
    "lang": "in",
    "user": {
      "id_str": "1819071344",
      "name": "Rizky Pratama",
      "screen_name": "rizkprat2409",
      "followers_count": 1272,
      "verified": false
    },
    "retweet_count": 3,
    "favorite_count": 79,
    "source": "Twitter Web App",
    "_meta": {
      "sentiment": "neutral",
      "aspect": "umum",
      "product": "ML Road Seat/Saddle",
      "category": "Unknown",
      "subcategory": "Unknown",
      "product_bias": "loved",
      "spike": false
    }
  },
  {
    "id_str": "1800000000000224087",
    "created_at": "2025-05-23T15:41:09Z",
    "text": "Really disappointed with the ML Mountain Tire — it broke after two weeks Do better AWC. 🙄",
    "lang": "en",
    "user": {
      "id_str": "9374938680",
      "name": "Jordan Hidayat",
      "screen_name": "jordhida9562",
      "followers_count": 370,
      "verified": false
    },
    "retweet_count": 15,
    "favorite_count": 18,
    "source": "Twitter Web App",
    "_meta": {
      "sentiment": "negative",
      "aspect": "durabilitas",
      "product": "ML Mountain Tire",
      "category": "Unknown",
      "subcategory": "Unknown",
      "product_bias": "problem",
      "spike": false
    }
  },
  {
    "id_str": "1800000000000224186",
    "created_at": "2025-05-23T16:22:57Z",
    "text": "HL Crankset dari @AWCycles mantap sih — masih awet setelah berbulan-bulan Nggak nyesel. 🚴",
    "lang": "in",
    "user": {
      "id_str": "2608793665",
      "name": "Alex Santoso",
      "screen_name": "alexsant2128",
      "followers_count": 309,
      "verified": false
    },
    "retweet_count": 17,
    "favorite_count": 25,
    "source": "Twitter Web App",
    "_meta": {
      "sentiment": "positive",
      "aspect": "durabilitas",
      "product": "HL Crankset",
      "category": "Unknown",
      "subcategory": "Unknown",
      "product_bias": "mixed",
      "spike": false
    }
  },
  {
    "id_str": "1800000000000224118",
    "created_at": "2025-05-23T17:50:41Z",
    "text": "Really impressed with the Half-Finger Gloves — build quality feels premium Will buy again. ✨ #cycling #AWcycles",
    "lang": "en",
    "user": {
      "id_str": "9283162080",
      "name": "Andi Pratama",
      "screen_name": "andiprat7161",
      "followers_count": 1018,
      "verified": false
    },
    "retweet_count": 14,
    "favorite_count": 9,
    "source": "Twitter for Android",
    "_meta": {
      "sentiment": "positive",
      "aspect": "kualitas",
      "product": "Half-Finger Gloves, S",
      "category": "Unknown",
      "subcategory": "Unknown",
      "product_bias": "mixed",
      "spike": false
    }
  },
  {
    "id_str": "1800000000000224125",
    "created_at": "2025-05-23T19:45:13Z",
    "text": "Really impressed with the HL Road Rear Wheel — feels solid and well made ✨",
    "lang": "en",
    "user": {
      "id_str": "8018228193",
      "name": "Sofia Clark",
      "screen_name": "soficlar2257",
      "followers_count": 1515,
      "verified": false
    },
    "retweet_count": 5,
    "favorite_count": 25,
    "source": "Twitter for iPhone",
    "_meta": {
      "sentiment": "positive",
      "aspect": "kualitas",
      "product": "HL Road Rear Wheel",
      "category": "Unknown",
      "subcategory": "Unknown",
      "product_bias": "mixed",
      "spike": false
    }
  },
  {
    "id_str": "1800000000000224181",
    "created_at": "2025-05-23T20:15:21Z",
    "text": "RT @mari79: Shoutout to @AWCycles for the Thin-Jam Lock Nut 11 — performs flawlessly 💯",
    "lang": "en",
    "user": {
      "id_str": "1818845157",
      "name": "Galih Saputra",
      "screen_name": "galisapu6779",
      "followers_count": 1415,
      "verified": false
    },
    "retweet_count": 12,
    "favorite_count": 26,
    "source": "Twitter for Android",
    "_meta": {
      "sentiment": "positive",
      "aspect": "kualitas",
      "product": "Thin-Jam Lock Nut 11",
      "category": "Unknown",
      "subcategory": "Unknown",
      "product_bias": "problem",
      "spike": false
    }
  }
]