[
  {
    "id_str": "1800000000000215760",
    "created_at": "2025-04-12T00:43:36Z",
    "text": "Anyone using the Road-550-W Yellow from @AWCycles? Worth it? 🤔 #MTB #bikelife #cycling #Unknown",
    "lang": "en",
    "user": {
      "id_str": "393166316",
      "name": "Rizky Santoso",
      "screen_name": "rizksant2989",
      "followers_count": 1592,
      "verified": false
    },
    "retweet_count": 0,
    "favorite_count": 1,
    "source": "Twitter Web App",
    "_meta": {
      "sentiment": "neutral",
      "aspect": "umum",
      "product": "Road-550-W Yellow, 48",
      "category": "Unknown",
      "subcategory": "Unknown",
      "product_bias": "loved",
      "spike": false
    }
  },
  {
    "id_str": "1800000000000215821",
    "created_at": "2025-04-12T06:54:42Z",
    "text": "Akhirnya pakai HL Mountain Frame - Black dan puas pol — puas pol Recommended. 💯 #bikelife #AdventureWorks #Unknown",
    "lang": "in",
    "user": {
      "id_str": "2898057506",
      "name": "Mia Santoso",
      "screen_name": "miasant8834",
      "followers_count": 4306,
      "verified": false
    },
    "retweet_count": 2,
    "favorite_count": 9,
    "source": "Twitter Web App",
    "_meta": {
      "sentiment": "positive",
      "aspect": "umum",
      "product": "HL Mountain Frame - Black, 48",
      "category": "Unknown",
      "subcategory": "Unknown",
      "product_bias": "loved",
      "spike": false
    }
  },
  {
    "id_str": "1800000000000215747",
    "created_at": "2025-04-12T10:49:26Z",
    "text": "Nggak nyesel beli Mountain End Caps — tahan banting dipakai berat Recommended. 😍 #cycling #AdventureWorks",
    "lang": "in",
    "user": {
      "id_str": "6512127318",
      "name": "Budi Kim",
      "screen_name": "budikim3460",
      "followers_count": 1275,
      "verified": false
    },
    "retweet_count": 3,
    "favorite_count": 19,
    "source": "Twitter Web App",
    "_meta": {
      "sentiment": "positive",
      "aspect": "durabilitas",
      "product": "Mountain End Caps",
      "category": "Unknown",
      "subcategory": "Unknown",
      "product_bias": "loved",
      "spike": false
    }
  },
  {
    "id_str": "1800000000000215953",
    "created_at": "2025-04-12T18:03:15Z",
    "text": "Road-250 Black dari AdventureWorks mantap sih — harga sebanding kualitas 👍 #cycling #bikes #rideon #Unknown",
    "lang": "in",
    "user": {
      "id_str": "4638327911",
      "name": "Nadia Hidayat",
      "screen_name": "nadihida8921",
      "followers_count": 1469,
      "verified": false
    },
    "retweet_count": 4,
    "favorite_count": 3,
    "source": "Twitter for iPhone",
    "_meta": {
      "sentiment": "positive",
      "aspect": "harga",
      "product": "Road-250 Black, 44",
      "category": "Unknown",
      "subcategory": "Unknown",
      "product_bias": "loved",
      "spike": false
    }
  },
  {
    "id_str": "1800000000000215753",
    "created_at": "2025-04-12T18:55:43Z",
    "text": "RT @chri85: Absolutely loving my new Touring-3000 Blue from @AWCycles — build quality feels premium Zero regrets. #rideon",
    "lang": "en",
    "user": {
      "id_str": "4425020575",
      "name": "Rizky Anwar",
      "screen_name": "rizkanwa6145",
      "followers_count": 223,
      "verified": false
    },
    "retweet_count": 23,
    "favorite_count": 17,
    "source": "Twitter for Android",
    "_meta": {
      "sentiment": "positive",
      "aspect": "kualitas",
      "product": "Touring-3000 Blue, 54",
      "category": "Unknown",
      "subcategory": "Unknown",
      "product_bias": "loved",
      "spike": false
    }
  },
  {
    "id_str": "1800000000000215869",
    "created_at": "2025-04-12T21:20:03Z",
    "text": "Lock Nut 7 dari AdventureWorks Cycles mantap sih — kirimnya lancar Nggak nyesel. 😍",
    "lang": "in",
    "user": {
      "id_str": "3117905199",
      "name": "Rizky Halim",
      "screen_name": "rizkhali8340",
      "followers_count": 3333,
      "verified": false
    },
    "retweet_count": 11,
    "favorite_count": 11,
    "source": "Twitter Web App",
    "_meta": {
      "sentiment": "positive",
      "aspect": "pengiriman",
      "product": "Lock Nut 7",
      "category": "Unknown",
      "subcategory": "Unknown",
      "product_bias": "mixed",
      "spike": false
    }
  },
  {
    "id_str": "1800000000000215906",
    "created_at": "2025-04-12T21:50:38Z",
    "text": "Capek deh sama Lock Nut 11 dari @AdventureWorks — finishing-nya asal 😣",
    "lang": "in",
    "user": {
      "id_str": "6005564557",
      "name": "Kevin Anwar",
      "screen_name": "kevianwa2655",
      "followers_count": 2651,
      "verified": false
    },
    "retweet_count": 0,
    "favorite_count": 6,
    "source": "Twitter Web App",
    "_meta": {
      "sentiment": "negative",
      "aspect": "kualitas",
      "product": "Lock Nut 11",
      "category": "Unknown",
      "subcategory": "Unknown",
      "product_bias": "problem",
      "spike": false
    }
  },
  {
    "id_str": "1800000000000215785",
    "created_at": "2025-04-12T23:17:05Z",
    "text": "Suka banget sama Mountain-100 Silver dari @AdventureWorks — murah buat kualitas segini Nggak nyesel. #cycling #AWcycles",
    "lang": "in",
    "user": {
      "id_str": "9380229887",
      "name": "Olivia Halim",
      "screen_name": "olivhali7893",
      "followers_count": 1245,
      "verified": false
    },
    "retweet_count": 2,
    "favorite_count": 11,
    "source": "Twitter Web App",
    "_meta": {
      "sentiment": "positive",
      "aspect": "harga",
      "product": "Mountain-100 Silver, 48",
      "category": "Unknown",
      "subcategory": "Unknown",
      "product_bias": "loved",
      "spike": false
    }
  }
]