[
  {
    "id_str": "1800000000000210403",
    "created_at": "2025-03-17T07:07:21Z",
    "text": "Really impressed with the LL Mountain Rear Wheel — support was quick and friendly Five stars. 😎 #AdventureWorks #Unknown",
    "lang": "en",
    "user": {
      "id_str": "3955032411",
      "name": "Eko Nguyen",
      "screen_name": "ekonguy74",
      "followers_count": 488,
      "verified": false
    },
    "retweet_count": 3,
    "favorite_count": 19,
    "source": "Twitter for Android",
    "_meta": {
      "sentiment": "positive",
      "aspect": "layanan",
      "product": "LL Mountain Rear Wheel",
      "category": "Unknown",
      "subcategory": "Unknown",
      "product_bias": "problem",
      "spike": false
    }
  },
  {
    "id_str": "1800000000000210331",
    "created_at": "2025-03-17T08:21:51Z",
    "text": "Akhirnya pakai Hex Nut 11 dan puas pol — harga sebanding kualitas ✨",
    "lang": "in",
    "user": {
      "id_str": "7367770675",
      "name": "Tom Brown",
      "screen_name": "tombrow2132",
      "followers_count": 2074,
      "verified": false
    },
    "retweet_count": 2,
    "favorite_count": 51,
    "source": "Twitter Web App",
    "_meta": {
      "sentiment": "positive",
      "aspect": "harga",
      "product": "Hex Nut 11",
      "category": "Unknown",
      "subcategory": "Unknown",
      "product_bias": "loved",
      "spike": false
    }
  },
  {
    "id_str": "1800000000000210384",
    "created_at": "2025-03-17T08:25:52Z",
    "text": "RT @dewi37: Udah sebulan pakai Taillights - Battery-Powered, oke terus — terasa kokoh dan rapi Recommended. 💯",
    "lang": "in",
    "user": {
      "id_str": "9997215075",
      "name": "Budi Smith",
      "screen_name": "budismit5406",
      "followers_count": 1465,
      "verified": false
    },
    "retweet_count": 2,
    "favorite_count": 11,
    "source": "Twitter Web App",
    "_meta": {
      "sentiment": "positive",
      "aspect": "kualitas",
      "product": "Taillights - Battery-Powered",
      "category": "Unknown",
      "subcategory": "Unknown",
      "product_bias": "problem",
      "spike": false
    }
  },
  {
    "id_str": "1800000000000210361",
    "created_at": "2025-03-17T09:23:42Z",
    "text": "Salut buat @AWCycles soal ML Mountain Frame-W - Silver — terasa kokoh dan rapi ✨ #MTB",
    "lang": "in",
    "user": {
      "id_str": "4870587373",
      "name": "Galih Pratama",
      "screen_name": "galiprat8011",
      "followers_count": 1540,
      "verified": false
    },
    "retweet_count": 2,
    "favorite_count": 32,
    "source": "Twitter for iPhone",
    "_meta": {
      "sentiment": "positive",
      "aspect": "kualitas",
      "product": "ML Mountain Frame-W - Silver, 46",
      "category": "Unknown",
      "subcategory": "Unknown",
      "product_bias": "problem",
      "spike": false
    }
  },
  {
    "id_str": "1800000000000210215",
    "created_at": "2025-03-17T10:56:09Z",
    "text": "My Lock Nut 11 from AWC is excellent — arrived a day early, well packed Zero regrets. ✨",
    "lang": "en",
    "user": {
      "id_str": "5604956087",
      "name": "Budi Saputra",
      "screen_name": "budisapu1695",
      "followers_count": 2635,
      "verified": false
    },
    "retweet_count": 12,
    "favorite_count": 16,
    "source": "Twitter for Android",
    "_meta": {
      "sentiment": "positive",
      "aspect": "pengiriman",
      "product": "Lock Nut 11",
      "category": "Unknown",
      "subcategory": "Unknown",
      "product_bias": "problem",
      "spike": false
    }
  },
  {
    "id_str": "1800000000000210291",
    "created_at": "2025-03-17T13:17:33Z",
    "text": "Baru unboxing Hex Nut 23, nanti aku update",
    "lang": "in",
    "user": {
      "id_str": "6245213414",
      "name": "Eko Putra",
      "screen_name": "ekoputr982",
      "followers_count": 2451,
      "verified": false
    },
    "retweet_count": 0,
    "favorite_count": 39,
    "source": "Twitter for Android",
    "_meta": {
      "sentiment": "neutral",
      "aspect": "umum",
      "product": "Hex Nut 23",
      "category": "Unknown",
      "subcategory": "Unknown",
      "product_bias": "mixed",
      "spike": false
    }
  },
  {
    "id_str": "1800000000000210254",
    "created_at": "2025-03-17T18:29:06Z",
    "text": "Absolutely loving my new ML Road Frame - Red from @AdventureWorks — worth every penny 🙌 #AWcycles #cycling #bikes",
    "lang": "en",
    "user": {
      "id_str": "1286627892",
      "name": "Eko Garcia",
      "screen_name": "ekogarc5434",
      "followers_count": 1483,
      "verified": false
    },
    "retweet_count": 8,
    "favorite_count": 25,
    "source": "Twitter for Android",
    "_meta": {
      "sentiment": "positive",
      "aspect": "harga",
      "product": "ML Road Frame - Red, 52",
      "category": "Unknown",
      "subcategory": "Unknown",
      "product_bias": "loved",
      "spike": false
    }
  },
  {
    "id_str": "1800000000000210267",
    "created_at": "2025-03-17T18:40:59Z",
    "text": "Really impressed with the Thin-Jam Hex Nut 16 — shipping was fast and packaging perfect Will buy again. 🔥 #AdventureWorks #rideon #MTB",
    "lang": "en",
    "user": {
      "id_str": "1239678596",
      "name": "Mia Pratama",
      "screen_name": "miaprat2658",
      "followers_count": 1911,
      "verified": false
    },
    "retweet_count": 22,
    "favorite_count": 32,
    "source": "Twitter for Android",
    "_meta": {
      "sentiment": "positive",
      "aspect": "pengiriman",
      "product": "Thin-Jam Hex Nut 16",
      "category": "Unknown",
      "subcategory": "Unknown",
      "product_bias": "loved",
      "spike": false
    }
  }
]