[
  {
    "id_str": "1800000000000131308",
    "created_at": "2024-03-01T07:13:58Z",
    "text": "Capek deh sama LL Grip Tape dari @AdventureWorks — zonk total 😩 #bikelife #MTB #cycling #Unknown",
    "lang": "in",
    "user": {
      "id_str": "6746173376",
      "name": "Raka Wijaya",
      "screen_name": "rakawija6941",
      "followers_count": 1323,
      "verified": true
    },
    "retweet_count": 13,
    "favorite_count": 8,
    "source": "Twitter for Android",
    "_meta": {
      "sentiment": "negative",
      "aspect": "umum",
      "product": "LL Grip Tape",
      "category": "Unknown",
      "subcategory": "Unknown",
      "product_bias": "mixed",
      "spike": false
    }
  },
  {
    "id_str": "1800000000000131375",
    "created_at": "2024-03-01T07:18:03Z",
    "text": "Nyesel beli Lock Nut 1 — packing-nya berantakan Hindari. #bikelife #bikes #AdventureWorks #Unknown",
    "lang": "in",
    "user": {
      "id_str": "8602447153",
      "name": "Dimas Smith",
      "screen_name": "dimasmit4603",
      "followers_count": 588,
      "verified": false
    },
    "retweet_count": 6,
    "favorite_count": 36,
    "source": "Twitter for iPhone",
    "_meta": {
      "sentiment": "negative",
      "aspect": "pengiriman",
      "product": "Lock Nut 1",
      "category": "Unknown",
      "subcategory": "Unknown",
      "product_bias": "problem",
      "spike": false
    }
  },
  {
    "id_str": "1800000000000131122",
    "created_at": "2024-03-01T07:32:25Z",
    "text": "Shoutout to AdventureWorks for the Hex Nut 17 — couldn't be happier ✨",
    "lang": "en",
    "user": {
      "id_str": "5053933983",
      "name": "Chris Lopez",
      "screen_name": "chrilope7046",
      "followers_count": 624,
      "verified": false
    },
    "retweet_count": 6,
    "favorite_count": 4,
    "source": "Twitter for Android",
    "_meta": {
      "sentiment": "positive",
      "aspect": "umum",
      "product": "Hex Nut 17",
      "category": "Unknown",
      "subcategory": "Unknown",
      "product_bias": "loved",
      "spike": false
    }
  },
  {
    "id_str": "1800000000000131265",
    "created_at": "2024-03-01T07:45:46Z",
    "text": "Just unboxed the HL Mountain Frame - Silver, will report back 🤷 #MTB #AWcycles #Unknown",
    "lang": "en",
    "user": {
      "id_str": "3172572720",
      "name": "Putri Putra",
      "screen_name": "putrputr9279",
      "followers_count": 311,
      "verified": false
    },
    "retweet_count": 23,
    "favorite_count": 4,
    "source": "Twitter for iPhone",
    "_meta": {
      "sentiment": "neutral",
      "aspect": "umum",
      "product": "HL Mountain Frame - Silver, 38",
      "category": "Unknown",
      "subcategory": "Unknown",
      "product_bias": "loved",
      "spike": false
    }
  },
  {
    "id_str": "1800000000000131221",
    "created_at": "2024-03-01T12:38:46Z",
    "text": "Upgraded to the Hex Nut 4 and no looking back — worth every penny Five stars. 😍",
    "lang": "en",
    "user": {
      "id_str": "8908187466",
      "name": "Rizky Lee",
      "screen_name": "rizklee784",
      "followers_count": 2680,
      "verified": false
    },
    "retweet_count": 1,
    "favorite_count": 6,
    "source": "Twitter Web App",
    "_meta": {
      "sentiment": "positive",
      "aspect": "harga",
      "product": "Hex Nut 4",
      "category": "Unknown",
      "subcategory": "Unknown",
      "product_bias": "mixed",
      "spike": false
    }
  },
  {
    "id_str": "1800000000000131143",
    "created_at": "2024-03-01T16:35:45Z",
    "text": "RT @lina34: Chainring dari AWC mantap sih — beli yang tepat sih 🙌 #cycling",
    "lang": "in",
    "user": {
      "id_str": "5910066084",
      "name": "Putri Kim",
      "screen_name": "putrkim4285",
      "followers_count": 83,
      "verified": false
    },
    "retweet_count": 2,
    "favorite_count": 1,
    "source": "Twitter Web App",
    "_meta": {
      "sentiment": "positive",
      "aspect": "umum",
      "product": "Chainring",
      "category": "Unknown",
      "subcategory": "Unknown",
      "product_bias": "loved",
      "spike": false
    }
  },
  {
    "id_str": "1800000000000131186",
    "created_at": "2024-03-01T17:52:28Z",
    "text": "Lock Nut 9 dari @AdventureWorks bikin nyesel — rusak baru dua minggu Pelajaran mahal. 😤",
    "lang": "in",
    "user": {
      "id_str": "3383029698",
      "name": "Kevin Pratama",
      "screen_name": "keviprat2827",
      "followers_count": 2428,
      "verified": false
    },
    "retweet_count": 0,
    "favorite_count": 2,
    "source": "Twitter Web App",
    "_meta": {
      "sentiment": "negative",
      "aspect": "durabilitas",
      "product": "Lock Nut 9",
      "category": "Unknown",
      "subcategory": "Unknown",
      "product_bias": "mixed",
      "spike": false
    }
  },
  {
    "id_str": "1800000000000131341",
    "created_at": "2024-03-01T20:44:50Z",
    "text": "Not happy with my External Lock Washer 9 at all — fell apart on the first ride 😩 #cycling #Unknown",
    "lang": "en",
    "user": {
      "id_str": "6394420496",
      "name": "Lina Santoso",
      "screen_name": "linasant6516",
      "followers_count": 21,
      "verified": false
    },
    "retweet_count": 1,
    "favorite_count": 33,
    "source": "Twitter Web App",
    "_meta": {
      "sentiment": "negative",
      "aspect": "durabilitas",
      "product": "External Lock Washer 9",
      "category": "Unknown",
      "subcategory": "Unknown",
      "product_bias": "problem",
      "spike": false
    }
  }
]