[
  {
    "id_str": "1800000000000180170",
    "created_at": "2024-10-22T08:07:31Z",
    "text": "Upgraded to the HL Road Frame - Red and no looking back — support was quick and friendly Zero regrets. 😎",
    "lang": "en",
    "user": {
      "id_str": "9225842293",
      "name": "Hannah Anwar",
      "screen_name": "hannanwa5150",
      "followers_count": 949,
      "verified": false
    },
    "retweet_count": 17,
    "favorite_count": 29,
    "source": "Twitter for Android",
    "_meta": {
      "sentiment": "positive",
      "aspect": "layanan",
      "product": "HL Road Frame - Red, 48",
      "category": "Unknown",
      "subcategory": "Unknown",
      "product_bias": "mixed",
      "spike": false
    }
  },
  {
    "id_str": "1800000000000180100",
    "created_at": "2024-10-22T10:01:24Z",
    "text": "Akhirnya pakai Touring-2000 Blue dan puas pol — kualitasnya premium 🚴 #AdventureWorks #Unknown",
    "lang": "in",
    "user": {
      "id_str": "9096450711",
      "name": "Bayu Smith",
      "screen_name": "bayusmit5729",
      "followers_count": 2047,
      "verified": false
    },
    "retweet_count": 2,
    "favorite_count": 6,
    "source": "Twitter for Android",
    "_meta": {
      "sentiment": "positive",
      "aspect": "kualitas",
      "product": "Touring-2000 Blue, 46",
      "category": "Unknown",
      "subcategory": "Unknown",
      "product_bias": "mixed",
      "spike": false
    }
  },
  {
    "id_str": "1800000000000180046",
    "created_at": "2024-10-22T10:30:56Z",
    "text": "Udahan deh sama Chain Stays ini — bunyi-bunyi dan ringkih Pelajaran mahal. 😡",
    "lang": "in",
    "user": {
      "id_str": "1776116661",
      "name": "Maria Nguyen",
      "screen_name": "maringuy9847",
      "followers_count": 797,
      "verified": false
    },
    "retweet_count": 7,
    "favorite_count": 29,
    "source": "Twitter for Android",
    "_meta": {
      "sentiment": "negative",
      "aspect": "kualitas",
      "product": "Chain Stays",
      "category": "Unknown",
      "subcategory": "Unknown",
      "product_bias": "loved",
      "spike": false
    }
  },
  {
    "id_str": "1800000000000180143",
    "created_at": "2024-10-22T16:19:28Z",
    "text": "Three weeks on the HL Road Rim and I'm sold — performs flawlessly ✨",
    "lang": "en",
    "user": {
      "id_str": "7156247544",
      "name": "Lina Nguyen",
      "screen_name": "linanguy551",
      "followers_count": 879,
      "verified": false
    },
    "retweet_count": 32,
    "favorite_count": 1,
    "source": "Twitter for Android",
    "_meta": {
      "sentiment": "positive",
      "aspect": "kualitas",
      "product": "HL Road Rim",
      "category": "Unknown",
      "subcategory": "Unknown",
      "product_bias": "mixed",
      "spike": false
    }
  },
  {
    "id_str": "1800000000000180196",
    "created_at": "2024-10-22T18:20:41Z",
    "text": "Regret buying the External Lock Washer 9 — poor build, cheap materials Lesson learned. 😡",
    "lang": "en",
    "user": {
      "id_str": "3619889144",
      "name": "Budi Santoso",
      "screen_name": "budisant7219",
      "followers_count": 1520,
      "verified": false
    },
    "retweet_count": 5,
    "favorite_count": 7,
    "source": "Twitter for Android",
    "_meta": {
      "sentiment": "negative",
      "aspect": "kualitas",
      "product": "External Lock Washer 9",
      "category": "Unknown",
      "subcategory": "Unknown",
      "product_bias": "problem",
      "spike": false
    }
  },
  {
    "id_str": "1800000000000180233",
    "created_at": "2024-10-22T21:26:45Z",
    "text": "Upgraded to the LL Mountain Frame - Silver and no looking back — delivery was smooth 👍 #AWcycles #rideon",
    "lang": "en",
    "user": {
      "id_str": "5047151291",
      "name": "Chris Santoso",
      "screen_name": "chrisant92",
      "followers_count": 1740,
      "verified": false
    },
    "retweet_count": 14,
    "favorite_count": 28,
    "source": "Twitter for iPhone",
    "_meta": {
      "sentiment": "positive",
      "aspect": "pengiriman",
      "product": "LL Mountain Frame - Silver, 40",
      "category": "Unknown",
      "subcategory": "Unknown",
      "product_bias": "problem",
      "spike": false
    }
  },
  {
    "id_str": "1800000000000180052",
    "created_at": "2024-10-22T22:00:53Z",
    "text": "HL Touring Frame - Blue dari AWC mantap sih — kualitasnya premium #rideon",
    "lang": "in",
    "user": {
      "id_str": "986906319",
      "name": "Tom Smith",
      "screen_name": "tomsmit2523",
      "followers_count": 2319,
      "verified": false
    },
    "retweet_count": 1,
    "favorite_count": 30,
    "source": "Twitter for iPhone",
    "_meta": {
      "sentiment": "positive",
      "aspect": "kualitas",
      "product": "HL Touring Frame - Blue, 46",
      "category": "Unknown",
      "subcategory": "Unknown",
      "product_bias": "loved",
      "spike": false
    }
  },
  {
    "id_str": "1800000000000180073",
    "created_at": "2024-10-22T23:59:28Z",
    "text": "Absolutely loving my new HL Mountain Front Wheel from @AdventureWorks — shipping was fast and packaging perfect Will buy again. ✨",
    "lang": "en",
    "user": {
      "id_str": "2406722966",
      "name": "Maria Anwar",
      "screen_name": "marianwa8272",
      "followers_count": 490,
      "verified": false
    },
    "retweet_count": 4,
    "favorite_count": 9,
    "source": "Twitter for Android",
    "_meta": {
      "sentiment": "positive",
      "aspect": "pengiriman",
      "product": "HL Mountain Front Wheel",
      "category": "Unknown",
      "subcategory": "Unknown",
      "product_bias": "problem",
      "spike": false
    }
  }
]