[
  {
    "id_str": "1800000000000171694",
    "created_at": "2024-09-10T01:26:59Z",
    "text": "Three weeks on the Paint - Red and I'm sold — performs flawlessly Highly recommend. 🚴 #AWcycles #cycling #AdventureWorks",
    "lang": "en",
    "user": {
      "id_str": "9028491311",
      "name": "Tom Saputra",
      "screen_name": "tomsapu4368",
      "followers_count": 1989,
      "verified": false
    },
    "retweet_count": 3,
    "favorite_count": 15,
    "source": "Twitter Web App",
    "_meta": {
      "sentiment": "positive",
      "aspect": "kualitas",
      "product": "Paint - Red",
      "category": "Unknown",
      "subcategory": "Unknown",
      "product_bias": "mixed",
      "spike": false
    }
  },
  {
    "id_str": "1800000000000171649",
    "created_at": "2024-09-10T07:59:28Z",
    "text": "Expected so much more from the ML Mountain Rear Wheel — wore out way too fast Never again. 🙄 #AWcycles #Unknown",
    "lang": "en",
    "user": {
      "id_str": "730188032",
      "name": "Kevin Hidayat",
      "screen_name": "kevihida8520",
      "followers_count": 1777,
      "verified": false
    },
    "retweet_count": 7,
    "favorite_count": 9,
    "source": "Twitter for Android",
    "_meta": {
      "sentiment": "negative",
      "aspect": "durabilitas",
      "product": "ML Mountain Rear Wheel",
      "category": "Unknown",
      "subcategory": "Unknown",
      "product_bias": "problem",
      "spike": false
    }
  },
  {
    "id_str": "1800000000000171728",
    "created_at": "2024-09-10T14:31:51Z",
    "text": "Akhirnya pakai Decal 2 dan puas pol — murah buat kualitas segini 🙌 #AWcycles #cycling #bikes",
    "lang": "in",
    "user": {
      "id_str": "5904910436",
      "name": "Citra Lopez",
      "screen_name": "citrlope1741",
      "followers_count": 417,
      "verified": false
    },
    "retweet_count": 17,
    "favorite_count": 3,
    "source": "Twitter Web App",
    "_meta": {
      "sentiment": "positive",
      "aspect": "harga",
      "product": "Decal 2",
      "category": "Unknown",
      "subcategory": "Unknown",
      "product_bias": "mixed",
      "spike": false
    }
  },
  {
    "id_str": "1800000000000171615",
    "created_at": "2024-09-10T15:15:38Z",
    "text": "Thinking about the Reflector. Any reviews? 🧐 #AdventureWorks #Unknown",
    "lang": "en",
    "user": {
      "id_str": "6455690966",
      "name": "Dimas Anwar",
      "screen_name": "dimaanwa9434",
      "followers_count": 4622,
      "verified": false
    },
    "retweet_count": 7,
    "favorite_count": 9,
    "source": "Twitter for iPhone",
    "_meta": {
      "sentiment": "neutral",
      "aspect": "umum",
      "product": "Reflector",
      "category": "Unknown",
      "subcategory": "Unknown",
      "product_bias": "mixed",
      "spike": false
    }
  },
  {
    "id_str": "1800000000000171507",
    "created_at": "2024-09-10T15:33:25Z",
    "text": "RT @mia66: Akhirnya pakai Metal Sheet 1 dan puas pol — admin responsif banget 😍",
    "lang": "in",
    "user": {
      "id_str": "8368647728",
      "name": "Olivia Smith",
      "screen_name": "olivsmit5801",
      "followers_count": 1442,
      "verified": false
    },
    "retweet_count": 26,
    "favorite_count": 18,
    "source": "Twitter for Android",
    "_meta": {
      "sentiment": "positive",
      "aspect": "layanan",
      "product": "Metal Sheet 1",
      "category": "Unknown",
      "subcategory": "Unknown",
      "product_bias": "loved",
      "spike": false
    }
  },
  {
    "id_str": "1800000000000171568",
    "created_at": "2024-09-10T16:47:21Z",
    "text": "Terkesan banget sama Mountain-300 Black — CS-nya cepat dan ramah Bintang lima. 🔥",
    "lang": "in",
    "user": {
      "id_str": "3290112510",
      "name": "Eko Santoso",
      "screen_name": "ekosant1137",
      "followers_count": 902,
      "verified": false
    },
    "retweet_count": 10,
    "favorite_count": 22,
    "source": "Twitter for iPhone",
    "_meta": {
      "sentiment": "positive",
      "aspect": "layanan",
      "product": "Mountain-300 Black, 48",
      "category": "Unknown",
      "subcategory": "Unknown",
      "product_bias": "mixed",
      "spike": false
    }
  },
  {
    "id_str": "1800000000000171573",
    "created_at": "2024-09-10T19:00:43Z",
    "text": "Front Derailleur dari AdventureWorks Cycles bikin nyesel — nggak sebanding harganya 😣 #bikelife #rideon #bikes",
    "lang": "in",
    "user": {
      "id_str": "6852012172",
      "name": "Maria Hidayat",
      "screen_name": "marihida6519",
      "followers_count": 653,
      "verified": false
    },
    "retweet_count": 14,
    "favorite_count": 40,
    "source": "Twitter Web App",
    "_meta": {
      "sentiment": "negative",
      "aspect": "harga",
      "product": "Front Derailleur",
      "category": "Unknown",
      "subcategory": "Unknown",
      "product_bias": "mixed",
      "spike": false
    }
  },
  {
    "id_str": "1800000000000171527",
    "created_at": "2024-09-10T20:04:42Z",
    "text": "The LL Mountain Rear Wheel from AdventureWorks has been fantastic — feels solid and well made Highly recommend. 😎",
    "lang": "en",
    "user": {
      "id_str": "8735357533",
      "name": "Maria Saputra",
      "screen_name": "marisapu8480",
      "followers_count": 686,
      "verified": false
    },
    "retweet_count": 16,
    "favorite_count": 7,
    "source": "Twitter for Android",
    "_meta": {
      "sentiment": "positive",
      "aspect": "kualitas",
      "product": "LL Mountain Rear Wheel",
      "category": "Unknown",
      "subcategory": "Unknown",
      "product_bias": "problem",
      "spike": false
    }
  }
]